setup.py
proxygeneratorbil/main.py
proxygeneratorbil.egg-info/PKG-INFO
proxygeneratorbil.egg-info/SOURCES.txt
proxygeneratorbil.egg-info/dependency_links.txt
proxygeneratorbil.egg-info/top_level.txt